gopy/__init__.py
gopy/profile.py
gopy/dfs/__init__.py
gopy/dfs/all_factors.py
gopy/dfs/count_islands.py
gopy/dfs/pacific_atlantic.py
gopy/dfs/sudoku_solver.py
gopy/dfs/walls_and_gates.py
gopy/dynamicProgramming/__init__.py
gopy/dynamicProgramming/binomial.py
gopy/dynamicProgramming/fibonacci.py
gopy/dynamicProgramming/knapsack.py
gopy/dynamicProgramming/longest_common_subsequence.py
gopy/graph/Transitive_Closure_DFS.py
gopy/graph/__init__.py
gopy/graph/check_bipartite.py
gopy/graph/check_digraph_strongly_connected.py
gopy/graph/clone_graph.py
gopy/graph/cycle_detection.py
gopy/graph/dijkstra.py
gopy/graph/find_all_cliques.py
gopy/graph/find_path.py
gopy/graph/graph.py
gopy/graph/markov_chain.py
gopy/graph/minimum_spanning_tree.py
gopy/graph/path_between_two_vertices_in_digraph.py
gopy/graph/satisfiability.py
gopy/graph/tarjan.py
gopy/graph/traversal.py
gopy/search/__init__.py
gopy/search/bsearch.py
gopy/search/interpolation_search.py
gopy/search/jumpSearch.py
gopy/search/lsearch.py
gopy/search/quick_select.py
gopy/search/sentinel_linear_search.py
gopy/search/tabu_search.py
gopy/search/ternary.py
gopy/sorting/__init__.py
gopy/sorting/bogo.py
gopy/sorting/bubble.py
gopy/sorting/bucket.py
gopy/sorting/cocktail.py
gopy/sorting/comb.py
gopy/sorting/counting.py
gopy/sorting/gnome.py
gopy/sorting/heap.py
gopy/sorting/insertion.py
gopy/sorting/merge.py
gopy/sorting/quick.py
gopy/sorting/radix.py
gopy/sorting/selection.py
gopy/sorting/shell.py
gopy/strings/__init__.py
gopy/strings/knuth_morris_pratt.py
gopy/strings/naive_string_match.py
gopy/strings/rabin_karp.py
gopy-0.7.3.dist-info/LICENSE.txt
gopy-0.7.3.dist-info/METADATA
gopy-0.7.3.dist-info/WHEEL
gopy-0.7.3.dist-info/top_level.txt
gopy-0.7.3.dist-info/RECORD
