Metadata-Version: 2.1
Name: gopy
Version: 0.7.3
Summary: Python Data Structures and Algorithms
Home-page: https://github.com/strongSoda/gopy
Author: Imran Khan
Author-email: strongsoda2@gmail.com
License: MIT
Download-URL: https://github.com/strongSoda/gopy/archive/v0.7.3.tar.gz
Platform: UNKNOWN
Classifier: Development Status :: 3 - Alpha
Classifier: Intended Audience :: Developers
Classifier: Topic :: Software Development :: Build Tools
Classifier: License :: OSI Approved :: MIT License
Classifier: Programming Language :: Python :: 3
Classifier: Programming Language :: Python :: 3.4
Classifier: Programming Language :: Python :: 3.5
Classifier: Programming Language :: Python :: 3.6
Requires-Dist: snakeviz (>=2.0.1)
Requires-Dist: numpy (>=1.17.0)
